autorag/__init__.py
autorag/chunker.py
autorag/cli.py
autorag/dashboard.py
autorag/evaluator.py
autorag/node_line.py
autorag/parser.py
autorag/strategy.py
autorag/support.py
autorag/validator.py
autorag/web.py
autorag/data/__init__.py
autorag/data/chunk/__init__.py
autorag/data/chunk/base.py
autorag/data/chunk/langchain_chunk.py
autorag/data/chunk/llama_index_chunk.py
autorag/data/chunk/run.py
autorag/data/legacy/__init__.py
autorag/data/legacy/corpus/__init__.py
autorag/data/legacy/corpus/langchain.py
autorag/data/legacy/corpus/llama_index.py
autorag/data/legacy/qacreation/__init__.py
autorag/data/legacy/qacreation/base.py
autorag/data/legacy/qacreation/llama_index.py
autorag/data/legacy/qacreation/llama_index_default_prompt.txt
autorag/data/legacy/qacreation/ragas.py
autorag/data/legacy/qacreation/simple.py
autorag/data/parse/__init__.py
autorag/data/parse/base.py
autorag/data/parse/clova.py
autorag/data/parse/langchain_parse.py
autorag/data/parse/llamaparse.py
autorag/data/parse/run.py
autorag/data/parse/table_hybrid_parse.py
autorag/data/qa/__init__.py
autorag/data/qa/extract_evidence.py
autorag/data/qa/sample.py
autorag/data/qa/schema.py
autorag/data/qa/evolve/__init__.py
autorag/data/qa/evolve/llama_index_query_evolve.py
autorag/data/qa/evolve/openai_query_evolve.py
autorag/data/qa/evolve/prompt.py
autorag/data/qa/filter/__init__.py
autorag/data/qa/filter/dontknow.py
autorag/data/qa/filter/passage_dependency.py
autorag/data/qa/filter/prompt.py
autorag/data/qa/generation_gt/__init__.py
autorag/data/qa/generation_gt/base.py
autorag/data/qa/generation_gt/llama_index_gen_gt.py
autorag/data/qa/generation_gt/openai_gen_gt.py
autorag/data/qa/generation_gt/prompt.py
autorag/data/qa/query/__init__.py
autorag/data/qa/query/llama_gen_query.py
autorag/data/qa/query/openai_gen_query.py
autorag/data/qa/query/prompt.py
autorag/data/utils/__init__.py
autorag/data/utils/util.py
autorag/deploy/__init__.py
autorag/deploy/api.py
autorag/deploy/base.py
autorag/deploy/gradio.py
autorag-0.3.21.dist-info/METADATA
autorag-0.3.21.dist-info/WHEEL
autorag-0.3.21.dist-info/entry_points.txt
autorag-0.3.21.dist-info/licenses/LICENSE
autorag-0.3.21.dist-info/RECORD
