Metadata-Version: 2.4
Name: AutoRAG
Version: 0.3.21
Summary: Automatically Evaluate RAG pipelines with your own data. Find optimal structure for new RAG product.
Project-URL: Homepage, https://github.com/Marker-Inc-Korea/AutoRAG
Author-email: Marker-Inc <vkehfdl1@gmail.com>
License:                                  Apache License
License-File: LICENSE
Keywords: AutoML,AutoML-RAG,AutoRAG,RAG,autorag,evaluation,rag-auto,rag-evaluation
Classifier: Intended Audience :: Developers
Classifier: Intended Audience :: Information Technology
Classifier: Intended Audience :: Science/Research
Classifier: Programming Language :: Python :: 3.10
Classifier: Programming Language :: Python :: 3.11
Classifier: Programming Language :: Python :: 3.12
Classifier: Topic :: Scientific/Engineering :: Artificial Intelligence
Classifier: Topic :: Software Development :: Libraries
Classifier: Topic :: Software Development :: Libraries :: Python Modules
Requires-Python: >=3.10
Requires-Dist: aiohttp>=3.12.13
Requires-Dist: banks>=2.1.2
Requires-Dist: chromadb>=1.0.0
Requires-Dist: click>=8.2.1
Requires-Dist: cohere>=5.18.0
Requires-Dist: couchbase>=4.4.0
Requires-Dist: datasets>=3.5.1
Requires-Dist: emoji>=2.14.1
Requires-Dist: evaluate>=0.4.4
Requires-Dist: fastapi>=0.115.13
Requires-Dist: fastparquet>=2024.11.0
Requires-Dist: gradio>=5.34.2
Requires-Dist: grpcio-health-checking<1.68.0,>=1.66.2
Requires-Dist: grpcio-status<1.68.0,>=1.66.2
Requires-Dist: grpcio-tools<1.68.0,>=1.66.2
Requires-Dist: grpcio<1.68.0,>=1.66.2
Requires-Dist: ipykernel>=6.29.5
Requires-Dist: ipywidgets-bokeh>=1.6.0
Requires-Dist: ipywidgets>=8.1.7
Requires-Dist: langchain-community==0.2.19
Requires-Dist: langchain-core==0.2.43
Requires-Dist: langchain-unstructured==0.1.2
Requires-Dist: langchain-upstage==0.1.5
Requires-Dist: langsmith==0.1.147
Requires-Dist: llama-index-core>=0.12.42
Requires-Dist: llama-index-embeddings-ollama>=0.6.0
Requires-Dist: llama-index-embeddings-openai-like>=0.1.1
Requires-Dist: llama-index-embeddings-openai>=0.3.1
Requires-Dist: llama-index-llms-bedrock>=0.3.8
Requires-Dist: llama-index-llms-openai-like>=0.4.0
Requires-Dist: llama-index-llms-openai>=0.4.7
Requires-Dist: llama-index-readers-file>=0.4.9
Requires-Dist: llama-index-retrievers-bm25>=0.5.2
Requires-Dist: llama-index>=0.12.42
Requires-Dist: mixedbread-ai>=2.2.6
Requires-Dist: numpy==1.26.4
Requires-Dist: openai>=1.90.0
Requires-Dist: pandas>=2.2.3
Requires-Dist: panel>=1.7.1
Requires-Dist: pinecone[grpc]
Requires-Dist: pyarrow>=20.0.0
Requires-Dist: pydantic>=2.9.2
Requires-Dist: pymilvus>=2.6.0b0
Requires-Dist: pyngrok>=7.2.11
Requires-Dist: pyyaml>=6.0.2
Requires-Dist: qdrant-client>=1.12.1
Requires-Dist: quart>=0.20.0
Requires-Dist: rank-bm25>=0.2.2
Requires-Dist: rich>=14.0.0
Requires-Dist: rouge-score>=0.1.2
Requires-Dist: sacrebleu>=2.5.1
Requires-Dist: scikit-learn>=1.7.0
Requires-Dist: seaborn>=0.13.2
Requires-Dist: streamlit>=1.46.0
Requires-Dist: tiktoken>=0.9.0
Requires-Dist: tokenlog>=0.0.3
Requires-Dist: tqdm>=4.67.1
Requires-Dist: voyageai>=0.3.2
Requires-Dist: weaviate-client>=4.15.2
Provides-Extra: all
Requires-Dist: bert-score>=0.3.13; extra == 'all'
Requires-Dist: flagembedding>=1.2.11; extra == 'all'
Requires-Dist: jq>=1.9.1; extra == 'all'
Requires-Dist: kiwipiepy>=0.18.0; extra == 'all'
Requires-Dist: konlpy>=0.6.0; extra == 'all'
Requires-Dist: llama-index-embeddings-huggingface>=0.5.4; extra == 'all'
Requires-Dist: llama-index-llms-huggingface>=0.5.0; extra == 'all'
Requires-Dist: llama-index-llms-ollama>=0.6.0; extra == 'all'
Requires-Dist: llmlingua>=0.2.2; extra == 'all'
Requires-Dist: onnxruntime>=1.22.0; extra == 'all'
Requires-Dist: pdf2image>=1.17.0; extra == 'all'
Requires-Dist: pdfminer-six>=20250506; extra == 'all'
Requires-Dist: pdfplumber>=0.11.7; extra == 'all'
Requires-Dist: peft>=0.15.2; extra == 'all'
Requires-Dist: pymupdf>=1.26.1; extra == 'all'
Requires-Dist: pypdf2==2.12.1; extra == 'all'
Requires-Dist: sentence-transformers>=4.1.0; extra == 'all'
Requires-Dist: sentencepiece>=0.2.0; extra == 'all'
Requires-Dist: sudachidict-core; extra == 'all'
Requires-Dist: sudachipy>=0.6.8; extra == 'all'
Requires-Dist: torch>=2.7.1; extra == 'all'
Requires-Dist: transformers>=4.51.3; extra == 'all'
Requires-Dist: unstructured[pdf]>=0.17.2; extra == 'all'
Requires-Dist: vllm>=0.11.0; extra == 'all'
Provides-Extra: gpu
Requires-Dist: bert-score>=0.3.13; extra == 'gpu'
Requires-Dist: flagembedding>=1.2.11; extra == 'gpu'
Requires-Dist: llama-index-embeddings-huggingface>=0.5.4; extra == 'gpu'
Requires-Dist: llama-index-llms-huggingface>=0.5.0; extra == 'gpu'
Requires-Dist: llama-index-llms-ollama>=0.6.0; extra == 'gpu'
Requires-Dist: llmlingua>=0.2.2; extra == 'gpu'
Requires-Dist: onnxruntime>=1.22.0; extra == 'gpu'
Requires-Dist: peft>=0.15.2; extra == 'gpu'
Requires-Dist: sentence-transformers>=4.1.0; extra == 'gpu'
Requires-Dist: sentencepiece>=0.2.0; extra == 'gpu'
Requires-Dist: torch>=2.7.1; extra == 'gpu'
Requires-Dist: transformers>=4.51.3; extra == 'gpu'
Requires-Dist: vllm>=0.11.0; extra == 'gpu'
Provides-Extra: ja
Requires-Dist: sudachidict-core; extra == 'ja'
Requires-Dist: sudachipy>=0.6.8; extra == 'ja'
Provides-Extra: ko
Requires-Dist: kiwipiepy>=0.18.0; extra == 'ko'
Requires-Dist: konlpy>=0.6.0; extra == 'ko'
Provides-Extra: parse
Requires-Dist: jq>=1.9.1; extra == 'parse'
Requires-Dist: pdf2image>=1.17.0; extra == 'parse'
Requires-Dist: pdfminer-six>=20250506; extra == 'parse'
Requires-Dist: pdfplumber>=0.11.7; extra == 'parse'
Requires-Dist: pymupdf>=1.26.1; extra == 'parse'
Requires-Dist: pypdf2==2.12.1; extra == 'parse'
Requires-Dist: unstructured[pdf]>=0.17.2; extra == 'parse'
